optionvisualizer/__init__.py
optionvisualizer/animated_gifs.py
optionvisualizer/barriers.py
optionvisualizer/greeks.py
optionvisualizer/greeks_2d.py
optionvisualizer/greeks_3d.py
optionvisualizer/multi_payoffs.py
optionvisualizer/option_formulas.py
optionvisualizer/sensitivities.py
optionvisualizer/simple_payoffs.py
optionvisualizer/utilities.py
optionvisualizer/visualizer.py
optionvisualizer/visualizer_params.py
optionvisualizer-1.2.5.dist-info/licenses/LICENSE
optionvisualizer-1.2.5.dist-info/METADATA
optionvisualizer-1.2.5.dist-info/WHEEL
optionvisualizer-1.2.5.dist-info/top_level.txt
optionvisualizer-1.2.5.dist-info/RECORD
