Metadata-Version: 2.4
Name: optionvisualizer
Version: 1.2.5
Summary: Visualize option prices and sensitivities.
Home-page: https://github.com/GBERESEARCH/optionvisualizer
Author: GBERESEARCH
Author-email: gberesearch@gmail.com
License: MIT
License-File: LICENSE
Requires-Dist: numpy>=1.16.2
Requires-Dist: scipy>=1.4.1
Requires-Dist: matplotlib>=3.6.0
Requires-Dist: plotly>=4.3.0
Requires-Dist: pillow>=5.4.1
Dynamic: license-file
